Workbook

Sheet Clientes
A1: CodCliente | B1: NomeCliente | C1: CodRamoAtiv | D1: DescRamoAtiv | E1: CodFinalidVenda | F1: DescFinalidVenda | G1: Varejo | H1: Atacado | I1: Industria | J1: Servi‡o
A2: 1 | B2: IMA TECIDOS DA MODA LTDA | C2: 20 | D2: =LOOKUP(C2,RamoAtividade!A:A,RamoAtividade!B:B) -> OUTROS SEGMENTOS | E2: 1 | F2: =LOOKUP(E2,Finalidades!A:A,Finalidades!B:B) -> Envio para Deposito | G2: S | H2: N | I2: N | J2: N
A3: 17 | B3: VIACAO PASSARO VERDE LTDA | C3: 20 | D3: =LOOKUP(C3,RamoAtividade!A:A,RamoAtividade!B:B) -> OUTROS SEGMENTOS | E3: 0 | F3: =LOOKUP(E3,Finalidades!A:A,Finalidades!B:B) -> #N/A | G3: N | H3: N | I3: N | J3: N
A4: 58 | B4: IND COM CONF ITIMITHUS LTDA ME | C4: 8 | D4: =LOOKUP(C4,RamoAtividade!A:A,RamoAtividade!B:B) -> FACCIONISTA | E4: 0 | F4: =LOOKUP(E4,Finalidades!A:A,Finalidades!B:B) -> #N/A | G4: N | H4: N | I4: N | J4: N
A5: 72 | B5: KRINDGES INDUSTRIAL LTDA | C5: 20 | D5: =LOOKUP(C5,RamoAtividade!A:A,RamoAtividade!B:B) -> OUTROS SEGMENTOS | E5: 0 | F5: =LOOKUP(E5,Finalidades!A:A,Finalidades!B:B) -> #N/A | G5: N | H5: N | I5: N | J5: N
A6: 75 | B6: PEDRINHO TEC CONF LTDA | C6: 12 | D6: =LOOKUP(C6,RamoAtividade!A:A,RamoAtividade!B:B) -> MODA FESTA | E6: 0 | F6: =LOOKUP(E6,Finalidades!A:A,Finalidades!B:B) -> #N/A | G6: N | H6: N | I6: N | J6: N
A7: 81 | B7: TEC JOTALIRA LTDA | C7: 3 | D7: =LOOKUP(C7,RamoAtividade!A:A,RamoAtividade!B:B) -> CAMA, MESA,BANHO E ENXOVAL | E7: 0 | F7: =LOOKUP(E7,Finalidades!A:A,Finalidades!B:B) -> #N/A | G7: N | H7: N | I7: N | J7: N
A8: 84 | B8: WILLER APARECIDO CRUZ | C8: 0 | D8: =LOOKUP(C8,RamoAtividade!A:A,RamoAtividade!B:B) -> #N/A | E8: 0 | F8: =LOOKUP(E8,Finalidades!A:A,Finalidades!B:B) -> #N/A | G8: N | H8: N | I8: N | J8: N
A9: 95 | B9: CODE BLUE CONF E CALCADOS LTDA ME | C9: 17 | D9: =LOOKUP(C9,RamoAtividade!A:A,RamoAtividade!B:B) -> TECELAGEM | E9: 0 | F9: =LOOKUP(E9,Finalidades!A:A,Finalidades!B:B) -> #N/A | G9: N | H9: N | I9: N | J9: N
A10: 103 | B10: MARIA MARGARIDA V MONTEIRO ME | C10: 9 | D10: =LOOKUP(C10,RamoAtividade!A:A,RamoAtividade!B:B) -> FEIRANTE | E10: 0 | F10: =LOOKUP(E10,Finalidades!A:A,Finalidades!B:B) -> #N/A | G10: N | H10: N | I10: N | J10: N
A11: 113 | B11: CONF LASALA LTDA EPP | C11: 12 | D11: =LOOKUP(C11,RamoAtividade!A:A,RamoAtividade!B:B) -> MODA FESTA | E11: 0 | F11: =LOOKUP(E11,Finalidades!A:A,Finalidades!B:B) -> #N/A | G11: N | H11: N | I11: N | J11: N
A12: 118 | B12: ESPA€O TEXTIL LTDA | C12: 3 | D12: =LOOKUP(C12,RamoAtividade!A:A,RamoAtividade!B:B) -> CAMA, MESA,BANHO E ENXOVAL | E12: 0 | F12: =LOOKUP(E12,Finalidades!A:A,Finalidades!B:B) -> #N/A | G12: N | H12: N | I12: N | J12: N
A13: 119 | B13: COML TEC CONF ALMEIDA BRAGA LTDA | C13: 9 | D13: =LOOKUP(C13,RamoAtividade!A:A,RamoAtividade!B:B) -> FEIRANTE | E13: 0 | F13: =LOOKUP(E13,Finalidades!A:A,Finalidades!B:B) -> #N/A | G13: N | H13: N | I13: N | J13: N
... A2529: 25505 | B2529: MODA SHAPER LTDA ME | C2529: 20 | D2529: =LOOKUP(C2529,RamoAtividade!A:A,RamoAtividade!B:B) -> OUTROS SEGMENTOS | E2529: 0 | F2529: =LOOKUP(E2529,Finalidades!A:A,Finalidades!B:B) -> #N/A | G2529: N | H2529: N | I2529: N | J2529: N
A2530: 25506 | B2530: B27 JEANS CONF LTDA ME | C2530: 0 | D2530: =LOOKUP(C2530,RamoAtividade!A:A,RamoAtividade!B:B) -> #N/A | E2530: 0 | F2530: =LOOKUP(E2530,Finalidades!A:A,Finalidades!B:B) -> #N/A
A2531: 25509 | B2531: SERELEPE CONF LTDA EPP | C2531: 12 | D2531: =LOOKUP(C2531,RamoAtividade!A:A,RamoAtividade!B:B) -> MODA FESTA | E2531: 0 | F2531: =LOOKUP(E2531,Finalidades!A:A,Finalidades!B:B) -> #N/A | G2531: N | H2531: N | I2531: N | J2531: N
A2532: 25516 | B2532: ROSA MORENA CONF LTDA - ME | C2532: 0 | D2532: =LOOKUP(C2532,RamoAtividade!A:A,RamoAtividade!B:B) -> #N/A | E2532: 0 | F2532: =LOOKUP(E2532,Finalidades!A:A,Finalidades!B:B) -> #N/A
A2533: 25517 | B2533: JAC INDL DE MODAS LTDA | C2533: 12 | D2533: =LOOKUP(C2533,RamoAtividade!A:A,RamoAtividade!B:B) -> MODA FESTA | E2533: 0 | F2533: =LOOKUP(E2533,Finalidades!A:A,Finalidades!B:B) -> #N/A | G2533: N | H2533: N | I2533: N | J2533: N
A2534: 25520 | B2534: SORAYA ANDRADE PAULINO | C2534: 12 | D2534: =LOOKUP(C2534,RamoAtividade!A:A,RamoAtividade!B:B) -> MODA FESTA | E2534: 0 | F2534: =LOOKUP(E2534,Finalidades!A:A,Finalidades!B:B) -> #N/A | G2534: N | H2534: N | I2534: N | J2534: N
A2535: 25523 | B2535: CRISTIANE FELIPE RIBEIRO DE ARAUJO CORTES 01309848688 | C2535: 12 | D2535: =LOOKUP(C2535,RamoAtividade!A:A,RamoAtividade!B:B) -> MODA FESTA | E2535: 0 | F2535: =LOOKUP(E2535,Finalidades!A:A,Finalidades!B:B) -> #N/A | G2535: N | H2535: N | I2535: N | J2535: N
A2536: 25524 | B2536: R D LAY CS MODA FEMININA LTDA EPP | C2536: 12 | D2536: =LOOKUP(C2536,RamoAtividade!A:A,RamoAtividade!B:B) -> MODA FESTA | E2536: 0 | F2536: =LOOKUP(E2536,Finalidades!A:A,Finalidades!B:B) -> #N/A | G2536: N | H2536: N | I2536: N | J2536: N
A2537: 25528 | B2537: M C GONZALEZ SIMABULULO EPP | C2537: 12 | D2537: =LOOKUP(C2537,RamoAtividade!A:A,RamoAtividade!B:B) -> MODA FESTA | E2537: 0 | F2537: =LOOKUP(E2537,Finalidades!A:A,Finalidades!B:B) -> #N/A | G2537: N | H2537: N | I2537: N | J2537: N
A2538: 25529 | B2538: AR13 ARTIGOS DOS VESTUARIOS LTDA | C2538: 0 | D2538: =LOOKUP(C2538,RamoAtividade!A:A,RamoAtividade!B:B) -> #N/A | E2538: 0 | F2538: =LOOKUP(E2538,Finalidades!A:A,Finalidades!B:B) -> #N/A
A2539: 25538 | B2539: IND E COM DE CONF GUEDA LTDA | C2539: 20 | D2539: =LOOKUP(C2539,RamoAtividade!A:A,RamoAtividade!B:B) -> OUTROS SEGMENTOS | E2539: 0 | F2539: =LOOKUP(E2539,Finalidades!A:A,Finalidades!B:B) -> #N/A | G2539: N | H2539: N | I2539: N | J2539: N
A2540: 25545 | B2540: MAGALI LOUBAQUE CPF 035.215.126 - 90 ME | C2540: 6 | D2540: =LOOKUP(C2540,RamoAtividade!A:A,RamoAtividade!B:B) -> COM VAREJISTA DE TECIDOS | E2540: 0 | F2540: =LOOKUP(E2540,Finalidades!A:A,Finalidades!B:B) -> #N/A | G2540: N | H2540: N | I2540: N | J2540: N
A2541: 25546 | B2541: DANUBIO MALHAS LTDA ME | C2541: 12 | D2541: =LOOKUP(C2541,RamoAtividade!A:A,RamoAtividade!B:B) -> MODA FESTA | E2541: 0 | F2541: =LOOKUP(E2541,Finalidades!A:A,Finalidades!B:B) -> #N/A | G2541: N | H2541: N | I2541: N | J2541: N
A2542: 25547 | B2542: MARISOL VESTUµRIO SA | C2542: 12 | D2542: =LOOKUP(C2542,RamoAtividade!A:A,RamoAtividade!B:B) -> MODA FESTA | E2542: 0 | F2542: =LOOKUP(E2542,Finalidades!A:A,Finalidades!B:B) -> #N/A | G2542: N | H2542: N | I2542: N | J2542: N
A2543: 25549 | B2543: ONEIDA DE JESUS VAZ DE MELO-ME | C2543: 12 | D2543: =LOOKUP(C2543,RamoAtividade!A:A,RamoAtividade!B:B) -> MODA FESTA | E2543: 0 | F2543: =LOOKUP(E2543,Finalidades!A:A,Finalidades!B:B) -> #N/A | G2543: N | H2543: N | I2543: N | J2543: N
A2544: 25550 | B2544: R F COM DE TEC E RETALHOS LTDA EPP | C2544: 0 | D2544: =LOOKUP(C2544,RamoAtividade!A:A,RamoAtividade!B:B) -> #N/A | E2544: 0 | F2544: =LOOKUP(E2544,Finalidades!A:A,Finalidades!B:B) -> #N/A | G2544: N | H2544: N | I2544: N | J2544: N
A2545: 25551 | B2545: PETY MARILIA IND DE CONF LTDA - ME | C2545: 0 | D2545: =LOOKUP(C2545,RamoAtividade!A:A,RamoAtividade!B:B) -> #N/A | E2545: 0 | F2545: =LOOKUP(E2545,Finalidades!A:A,Finalidades!B:B) -> #N/A | G2545: N | H2545: N | I2545: N | J2545: N
A2546: 25564 | B2546: RENATO CALDEIRA FRANCO 71233725653 | C2546: 0 | D2546: =LOOKUP(C2546,RamoAtividade!A:A,RamoAtividade!B:B) -> #N/A | E2546: 0 | F2546: =LOOKUP(E2546,Finalidades!A:A,Finalidades!B:B) -> #N/A | G2546: N | H2546: N | I2546: N | J2546: N
A2547: 25566 | B2547: J T H MODAS LTDA | C2547: 12 | D2547: =LOOKUP(C2547,RamoAtividade!A:A,RamoAtividade!B:B) -> MODA FESTA | E2547: 0 | F2547: =LOOKUP(E2547,Finalidades!A:A,Finalidades!B:B) -> #N/A | G2547: N | H2547: N | I2547: N | J2547: N
A2548: 25573 | B2548: ELVIRA BEGNAMI CORREA 85592587600 | C2548: 0 | D2548: =LOOKUP(C2548,RamoAtividade!A:A,RamoAtividade!B:B) -> #N/A | E2548: 0 | F2548: =LOOKUP(E2548,Finalidades!A:A,Finalidades!B:B) -> #N/A
A2549: 25574 | B2549: EURIPEDES DONIZETE DA LUZ RESENDE ME | C2549: 0 | D2549: =LOOKUP(C2549,RamoAtividade!A:A,RamoAtividade!B:B) -> #N/A | E2549: 0 | F2549: =LOOKUP(E2549,Finalidades!A:A,Finalidades!B:B) -> #N/A | G2549: N | H2549: N | I2549: N | J2549: N
A2550: 25580 | B2550: M A F GOMES EPP | C2550: 12 | D2550: =LOOKUP(C2550,RamoAtividade!A:A,RamoAtividade!B:B) -> MODA FESTA | E2550: 0 | F2550: =LOOKUP(E2550,Finalidades!A:A,Finalidades!B:B) -> #N/A | G2550: N | H2550: N | I2550: N | J2550: N
A2551: 25581 | B2551: CASSIA TULIA OLIVEIRA URSINE SILVA - 388.486.196-49 - ME | C2551: 12 | D2551: =LOOKUP(C2551,RamoAtividade!A:A,RamoAtividade!B:B) -> MODA FESTA | E2551: 0 | F2551: =LOOKUP(E2551,Finalidades!A:A,Finalidades!B:B) -> #N/A | G2551: N | H2551: N | I2551: N | J2551: N
A2552: 25584 | B2552: ISAIAS LAGE DA LUZ 06464382632 | C2552: 12 | D2552: =LOOKUP(C2552,RamoAtividade!A:A,RamoAtividade!B:B) -> MODA FESTA | E2552: 0 | F2552: =LOOKUP(E2552,Finalidades!A:A,Finalidades!B:B) -> #N/A | G2552: N | H2552: N | I2552: N | J2552: N
A2553: 25592 | B2553: B & D CONF LT - ME | C2553: 12 | D2553: =LOOKUP(C2553,RamoAtividade!A:A,RamoAtividade!B:B) -> MODA FESTA | E2553: 0 | F2553: =LOOKUP(E2553,Finalidades!A:A,Finalidades!B:B) -> #N/A | G2553: N | H2553: N | I2553: N | J2553: N
A2554: 25594 | B2554: CRM INDUSTRIA TEXTIL LTDA | C2554: 0 | D2554: =LOOKUP(C2554,RamoAtividade!A:A,RamoAtividade!B:B) -> #N/A | E2554: 0 | F2554: =LOOKUP(E2554,Finalidades!A:A,Finalidades!B:B) -> #N/A | G2554: N | H2554: N | I2554: N | J2554: N
A2555: 25600 | B2555: POLLYMAR MODAS LTDA ME | C2555: 12 | D2555: =LOOKUP(C2555,RamoAtividade!A:A,RamoAtividade!B:B) -> MODA FESTA | E2555: 0 | F2555: =LOOKUP(E2555,Finalidades!A:A,Finalidades!B:B) -> #N/A | G2555: N | H2555: N | I2555: N | J2555: N
A2556: 25603 | B2556: SEGUNDA INTENCAO MODA INTIMA LTDA - ME | C2556: 12 | D2556: =LOOKUP(C2556,RamoAtividade!A:A,RamoAtividade!B:B) -> MODA FESTA | E2556: 0 | F2556: =LOOKUP(E2556,Finalidades!A:A,Finalidades!B:B) -> #N/A | G2556: N | H2556: N | I2556: N | J2556: N
A2557: 25605 | B2557: J F SANTOS SIQUEIRA ARAGAO | C2557: 12 | D2557: =LOOKUP(C2557,RamoAtividade!A:A,RamoAtividade!B:B) -> MODA FESTA | E2557: 0 | F2557: =LOOKUP(E2557,Finalidades!A:A,Finalidades!B:B) -> #N/A | G2557: N | H2557: N | I2557: N | J2557: N
A2558: 25613 | B2558: MENDONCA CARVALHO COM E IND DE CONF LTDA - | C2558: 12 | D2558: =LOOKUP(C2558,RamoAtividade!A:A,RamoAtividade!B:B) -> MODA FESTA | E2558: 0 | F2558: =LOOKUP(E2558,Finalidades!A:A,Finalidades!B:B) -> #N/A | G2558: N | H2558: N | I2558: N | J2558: N
A2559: 25618 | B2559: UNIFORGIS UNIFORMES PROFISSIONAIS LTDA ME | C2559: 0 | D2559: =LOOKUP(C2559,RamoAtividade!A:A,RamoAtividade!B:B) -> #N/A | E2559: 0 | F2559: =LOOKUP(E2559,Finalidades!A:A,Finalidades!B:B) -> #N/A | G2559: N | H2559: N | I2559: N | J2559: N
A2560: 25622 | B2560: EDNEIA APARECIDA DA SILVA OLIVEIRA 05898969624 | C2560: 0 | D2560: =LOOKUP(C2560,RamoAtividade!A:A,RamoAtividade!B:B) -> #N/A | E2560: 0 | F2560: =LOOKUP(E2560,Finalidades!A:A,Finalidades!B:B) -> #N/A | G2560: N | H2560: N | I2560: N | J2560: N
... A2568: 25641 | B2568: ACACIA TEC LTDA ME | C2568: 0 | D2568: =LOOKUP(C2568,RamoAtividade!A:A,RamoAtividade!B:B) -> #N/A | E2568: 0 | F2568: =LOOKUP(E2568,Finalidades!A:A,Finalidades!B:B) -> #N/A | G2568: N | H2568: N | I2568: N | J2568: N
A2569: 25644 | B2569: GENERALE COM E CONF DE ROUPAS LTDA | C2569: 0 | D2569: =LOOKUP(C2569,RamoAtividade!A:A,RamoAtividade!B:B) -> #N/A | E2569: 0 | F2569: =LOOKUP(E2569,Finalidades!A:A,Finalidades!B:B) -> #N/A
A2570: 25647 | B2570: SERGIO MOURA SANTOS CONF ME | C2570: 12 | D2570: =LOOKUP(C2570,RamoAtividade!A:A,RamoAtividade!B:B) -> MODA FESTA | E2570: 0 | F2570: =LOOKUP(E2570,Finalidades!A:A,Finalidades!B:B) -> #N/A | G2570: N | H2570: N | I2570: N | J2570: N
A2571: 25648 | B2571: MARTA VERONICA PEDROSA MOTA SA- ME | C2571: 12 | D2571: =LOOKUP(C2571,RamoAtividade!A:A,RamoAtividade!B:B) -> MODA FESTA | E2571: 0 | F2571: =LOOKUP(E2571,Finalidades!A:A,Finalidades!B:B) -> #N/A | G2571: N | H2571: N | I2571: N | J2571: N
A2572: 25650 | B2572: CONF LO ES LTDA EPP | C2572: 12 | D2572: =LOOKUP(C2572,RamoAtividade!A:A,RamoAtividade!B:B) -> MODA FESTA | E2572: 0 | F2572: =LOOKUP(E2572,Finalidades!A:A,Finalidades!B:B) -> #N/A | G2572: N | H2572: N | I2572: N | J2572: N
A2573: 25651 | B2573: GERSON RODRIGUES 65362225634 | C2573: 0 | D2573: =LOOKUP(C2573,RamoAtividade!A:A,RamoAtividade!B:B) -> #N/A | E2573: 0 | F2573: =LOOKUP(E2573,Finalidades!A:A,Finalidades!B:B) -> #N/A | G2573: N | H2573: N | I2573: N | J2573: N
A2574: 25659 | B2574: DEVENIR AMANCIO FAGUNDES ROUPAS | C2574: 6 | D2574: =LOOKUP(C2574,RamoAtividade!A:A,RamoAtividade!B:B) -> COM VAREJISTA DE TECIDOS | E2574: 0 | F2574: =LOOKUP(E2574,Finalidades!A:A,Finalidades!B:B) -> #N/A | G2574: N | H2574: N | I2574: N | J2574: N
A2575: 25661 | B2575: G Q FERREIRA CONF - ME | C2575: 12 | D2575: =LOOKUP(C2575,RamoAtividade!A:A,RamoAtividade!B:B) -> MODA FESTA | E2575: 0 | F2575: =LOOKUP(E2575,Finalidades!A:A,Finalidades!B:B) -> #N/A | G2575: N | H2575: N | I2575: N | J2575: N
A2576: 25662 | B2576: FLAVIA ADRIANA BELIZARIO DA SILVA 05226458606 | C2576: 12 | D2576: =LOOKUP(C2576,RamoAtividade!A:A,RamoAtividade!B:B) -> MODA FESTA | E2576: 0 | F2576: =LOOKUP(E2576,Finalidades!A:A,Finalidades!B:B) -> #N/A | G2576: N | H2576: N | I2576: N | J2576: N
A2577: 25672 | B2577: KESSEY COM E CONF DE ROUPAS LTDA. | C2577: 12 | D2577: =LOOKUP(C2577,RamoAtividade!A:A,RamoAtividade!B:B) -> MODA FESTA | E2577: 0 | F2577: =LOOKUP(E2577,Finalidades!A:A,Finalidades!B:B) -> #N/A | G2577: N | H2577: N | I2577: N | J2577: N
A2578: 25677 | B2578: MARIA CORINA DOS SANTOS 78199220791 | C2578: 12 | D2578: =LOOKUP(C2578,RamoAtividade!A:A,RamoAtividade!B:B) -> MODA FESTA | E2578: 0 | F2578: =LOOKUP(E2578,Finalidades!A:A,Finalidades!B:B) -> #N/A | G2578: N | H2578: N | I2578: N | J2578: N
A2579: 25678 | B2579: GELVA SOARES FERNANDES | C2579: 12 | D2579: =LOOKUP(C2579,RamoAtividade!A:A,RamoAtividade!B:B) -> MODA FESTA | E2579: 0 | F2579: =LOOKUP(E2579,Finalidades!A:A,Finalidades!B:B) -> #N/A | G2579: N | H2579: N | I2579: N | J2579: N
A2580: 25688 | B2580: ELENIR FERREIRA FREITAS 04788309637 | C2580: 12 | D2580: =LOOKUP(C2580,RamoAtividade!A:A,RamoAtividade!B:B) -> MODA FESTA | E2580: 0 | F2580: =LOOKUP(E2580,Finalidades!A:A,Finalidades!B:B) -> #N/A | G2580: N | H2580: N | I2580: N | J2580: N
A2581: 25689 | B2581: VINDICE IND DE CONF LTDA | C2581: 12 | D2581: =LOOKUP(C2581,RamoAtividade!A:A,RamoAtividade!B:B) -> MODA FESTA | E2581: 0 | F2581: =LOOKUP(E2581,Finalidades!A:A,Finalidades!B:B) -> #N/A | G2581: N | H2581: N | I2581: N | J2581: N
... A2940: 26729 | B2940: MARIA APARECIDA SALOME DE ARAUJO SOUZA 51023555620 | C2940: 0 | D2940: =LOOKUP(C2940,RamoAtividade!A:A,RamoAtividade!B:B) -> #N/A | E2940: 0 | F2940: =LOOKUP(E2940,Finalidades!A:A,Finalidades!B:B) -> #N/A | G2940: N | H2940: N | I2940: N | J2940: N
A2941: 26731 | B2941: W GEAR IND E COM DE ROUPAS LTDA | C2941: 0 | D2941: =LOOKUP(C2941,RamoAtividade!A:A,RamoAtividade!B:B) -> #N/A | E2941: 0 | F2941: =LOOKUP(E2941,Finalidades!A:A,Finalidades!B:B) -> #N/A
A2942: 26732 | B2942: COM DE CONF JOSEFA LTDA ME | C2942: 0 | D2942: =LOOKUP(C2942,RamoAtividade!A:A,RamoAtividade!B:B) -> #N/A | E2942: 0 | F2942: =LOOKUP(E2942,Finalidades!A:A,Finalidades!B:B) -> #N/A
A2943: 26735 | B2943: REY LUA IND E COM DE CONF LTDA ME | C2943: 0 | D2943: =LOOKUP(C2943,RamoAtividade!A:A,RamoAtividade!B:B) -> #N/A | E2943: 0 | F2943: =LOOKUP(E2943,Finalidades!A:A,Finalidades!B:B) -> #N/A
A2944: 26736 | B2944: ALICE RODRIGUES PAMPLONA | C2944: 0 | D2944: =LOOKUP(C2944,RamoAtividade!A:A,RamoAtividade!B:B) -> #N/A | E2944: 0 | F2944: =LOOKUP(E2944,Finalidades!A:A,Finalidades!B:B) -> #N/A
A2945: 26740 | B2945: VERA LUCIA RIBEIRO E SILVA ME | C2945: 12 | D2945: =LOOKUP(C2945,RamoAtividade!A:A,RamoAtividade!B:B) -> MODA FESTA | E2945: 0 | F2945: =LOOKUP(E2945,Finalidades!A:A,Finalidades!B:B) -> #N/A | G2945: N | H2945: N | I2945: N | J2945: N
A2946: 26745 | B2946: ANTONIO EGBERTO MESQUITA LOBO FILHO EPP | C2946: 12 | D2946: =LOOKUP(C2946,RamoAtividade!A:A,RamoAtividade!B:B) -> MODA FESTA | E2946: 0 | F2946: =LOOKUP(E2946,Finalidades!A:A,Finalidades!B:B) -> #N/A | G2946: N | H2946: N | I2946: N | J2946: N
A2947: 26746 | B2947: JOAO BATISTA DE SOUZA MIRANDA 29658691668 | C2947: 12 | D2947: =LOOKUP(C2947,RamoAtividade!A:A,RamoAtividade!B:B) -> MODA FESTA | E2947: 0 | F2947: =LOOKUP(E2947,Finalidades!A:A,Finalidades!B:B) -> #N/A | G2947: N | H2947: N | I2947: N | J2947: N
A2948: 26747 | B2948: GBF CONF LTDA ME | C2948: 12 | D2948: =LOOKUP(C2948,RamoAtividade!A:A,RamoAtividade!B:B) -> MODA FESTA | E2948: 0 | F2948: =LOOKUP(E2948,Finalidades!A:A,Finalidades!B:B) -> #N/A | G2948: N | H2948: N | I2948: N | J2948: N
A2949: 26748 | B2949: CRISTINA DE AGUILAR DA CRUZ 04088827600 | C2949: 12 | D2949: =LOOKUP(C2949,RamoAtividade!A:A,RamoAtividade!B:B) -> MODA FESTA | E2949: 0 | F2949: =LOOKUP(E2949,Finalidades!A:A,Finalidades!B:B) -> #N/A | G2949: N | H2949: N | I2949: N | J2949: N
A2950: 26749 | B2950: MARIA DE FATIMA PEREIRA 19608608600 | C2950: 0 | D2950: =LOOKUP(C2950,RamoAtividade!A:A,RamoAtividade!B:B) -> #N/A | E2950: 0 | F2950: =LOOKUP(E2950,Finalidades!A:A,Finalidades!B:B) -> #N/A
A2951: 26750 | B2951: EMPàRIO CR IND E COM DE CONF DO VEST L | C2951: 12 | D2951: =LOOKUP(C2951,RamoAtividade!A:A,RamoAtividade!B:B) -> MODA FESTA | E2951: 0 | F2951: =LOOKUP(E2951,Finalidades!A:A,Finalidades!B:B) -> #N/A | G2951: N | H2951: N | I2951: N | J2951: N
A2952: 26753 | B2952: ARAUJO & MELLER IND E COM DE CONF LTDA | C2952: 12 | D2952: =LOOKUP(C2952,RamoAtividade!A:A,RamoAtividade!B:B) -> MODA FESTA | E2952: 0 | F2952: =LOOKUP(E2952,Finalidades!A:A,Finalidades!B:B) -> #N/A | G2952: N | H2952: N | I2952: N | J2952: N
A2953: 26754 | B2953: ALEXANDRO DOS SANTOS MARROCOS - ME | C2953: 0 | D2953: =LOOKUP(C2953,RamoAtividade!A:A,RamoAtividade!B:B) -> #N/A | E2953: 0 | F2953: =LOOKUP(E2953,Finalidades!A:A,Finalidades!B:B) -> #N/A
A2954: 26755 | B2954: FIBRACOR TEC NACIONAIS E IMPORTADOS LTDA ME | C2954: 0 | D2954: =LOOKUP(C2954,RamoAtividade!A:A,RamoAtividade!B:B) -> #N/A | E2954: 0 | F2954: =LOOKUP(E2954,Finalidades!A:A,Finalidades!B:B) -> #N/A | G2954: N | H2954: N | I2954: N | J2954: N
A2955: 26756 | B2955: RHABASK IND COM DE ROUPAS PROFISSIONAIS LTDA ME | C2955: 0 | D2955: =LOOKUP(C2955,RamoAtividade!A:A,RamoAtividade!B:B) -> #N/A | E2955: 0 | F2955: =LOOKUP(E2955,Finalidades!A:A,Finalidades!B:B) -> #N/A | G2955: N | H2955: N | I2955: N | J2955: N
A2956: 26760 | B2956: VEST FASHION LTDA | C2956: 0 | D2956: =LOOKUP(C2956,RamoAtividade!A:A,RamoAtividade!B:B) -> #N/A | E2956: 0 | F2956: =LOOKUP(E2956,Finalidades!A:A,Finalidades!B:B) -> #N/A
A2957: 26762 | B2957: IGOR NUNES GOBBI 14122932785 | C2957: 0 | D2957: =LOOKUP(C2957,RamoAtividade!A:A,RamoAtividade!B:B) -> #N/A | E2957: 0 | F2957: =LOOKUP(E2957,Finalidades!A:A,Finalidades!B:B) -> #N/A
A2958: 26763 | B2958: VIP FASHION IND E COM DE CONF LTDA - ME | C2958: 0 | D2958: =LOOKUP(C2958,RamoAtividade!A:A,RamoAtividade!B:B) -> #N/A | E2958: 0 | F2958: =LOOKUP(E2958,Finalidades!A:A,Finalidades!B:B) -> #N/A
A2959: 26765 | B2959: DESIGUAL IND COM DE CONF LTDA | C2959: 12 | D2959: =LOOKUP(C2959,RamoAtividade!A:A,RamoAtividade!B:B) -> MODA FESTA | E2959: 0 | F2959: =LOOKUP(E2959,Finalidades!A:A,Finalidades!B:B) -> #N/A | G2959: N | H2959: N | I2959: N | J2959: N
A2960: 26767 | B2960: AMERICAN S CONF LTDA EPP | C2960: 12 | D2960: =LOOKUP(C2960,RamoAtividade!A:A,RamoAtividade!B:B) -> MODA FESTA | E2960: 0 | F2960: =LOOKUP(E2960,Finalidades!A:A,Finalidades!B:B) -> #N/A | G2960: N | H2960: N | I2960: N | J2960: N
A2961: 26768 | B2961: LACERDA ALIMENTACAO LTDA EPP | C2961: 0 | D2961: =LOOKUP(C2961,RamoAtividade!A:A,RamoAtividade!B:B) -> #N/A | E2961: 0 | F2961: =LOOKUP(E2961,Finalidades!A:A,Finalidades!B:B) -> #N/A | G2961: N | H2961: N | I2961: N | J2961: N
A2962: 26769 | B2962: STASTIE MODAS LTDA EPP | C2962: 12 | D2962: =LOOKUP(C2962,RamoAtividade!A:A,RamoAtividade!B:B) -> MODA FESTA | E2962: 0 | F2962: =LOOKUP(E2962,Finalidades!A:A,Finalidades!B:B) -> #N/A | G2962: N | H2962: N | I2962: N | J2962: N
A2963: 26772 | B2963: DI TRENTO IND E COM DE CONF LTDA EPP | C2963: 12 | D2963: =LOOKUP(C2963,RamoAtividade!A:A,RamoAtividade!B:B) -> MODA FESTA | E2963: 0 | F2963: =LOOKUP(E2963,Finalidades!A:A,Finalidades!B:B) -> #N/A | G2963: N | H2963: N | I2963: N | J2963: N
A2964: 26773 | B2964: MARIA JOSE GOMES REIS 03919118642 | C2964: 0 | D2964: =LOOKUP(C2964,RamoAtividade!A:A,RamoAtividade!B:B) -> #N/A | E2964: 0 | F2964: =LOOKUP(E2964,Finalidades!A:A,Finalidades!B:B) -> #N/A
A2965: 26774 | B2965: EXCLUSIVA TEC E RENDAS EIRELI - ME | C2965: 12 | D2965: =LOOKUP(C2965,RamoAtividade!A:A,RamoAtividade!B:B) -> MODA FESTA | E2965: 0 | F2965: =LOOKUP(E2965,Finalidades!A:A,Finalidades!B:B) -> #N/A | G2965: N | H2965: N | I2965: N | J2965: N
A2966: 26776 | B2966: AMERICAN PELL IND E COM DE BRINQ LTDA ME | C2966: 12 | D2966: =LOOKUP(C2966,RamoAtividade!A:A,RamoAtividade!B:B) -> MODA FESTA | E2966: 0 | F2966: =LOOKUP(E2966,Finalidades!A:A,Finalidades!B:B) -> #N/A | G2966: N | H2966: N | I2966: N | J2966: N
A2967: 26777 | B2967: ATELIER SANDRA FERNANDES LTDA ME | C2967: 0 | D2967: =LOOKUP(C2967,RamoAtividade!A:A,RamoAtividade!B:B) -> #N/A | E2967: 0 | F2967: =LOOKUP(E2967,Finalidades!A:A,Finalidades!B:B) -> #N/A | G2967: N | H2967: N | I2967: N | J2967: N
A2968: 26778 | B2968: JECV IND E COM DE CONF LTDA ME | C2968: 0 | D2968: =LOOKUP(C2968,RamoAtividade!A:A,RamoAtividade!B:B) -> #N/A | E2968: 0 | F2968: =LOOKUP(E2968,Finalidades!A:A,Finalidades!B:B) -> #N/A
A2969: 26781 | B2969: VANILLAMINT CONF DE ROUPAS LTDA | C2969: 12 | D2969: =LOOKUP(C2969,RamoAtividade!A:A,RamoAtividade!B:B) -> MODA FESTA | E2969: 0 | F2969: =LOOKUP(E2969,Finalidades!A:A,Finalidades!B:B) -> #N/A | G2969: N | H2969: N | I2969: N | J2969: N
A2970: 26782 | B2970: ARILUCE DE SOUZA LIMA COSTA | C2970: 0 | D2970: =LOOKUP(C2970,RamoAtividade!A:A,RamoAtividade!B:B) -> #N/A | E2970: 0 | F2970: =LOOKUP(E2970,Finalidades!A:A,Finalidades!B:B) -> #N/A | G2970: N | H2970: N | I2970: N | J2970: N
A2971: 26783 | B2971: LILIAN CARLA DOS SANTOS MARTINS COM DE TEC | C2971: 0 | D2971: =LOOKUP(C2971,RamoAtividade!A:A,RamoAtividade!B:B) -> #N/A | E2971: 0 | F2971: =LOOKUP(E2971,Finalidades!A:A,Finalidades!B:B) -> #N/A | G2971: N | H2971: N | I2971: N | J2971: N
A2972: 26784 | B2972: JOSE AQUILES RAMOS DE LIMA EPP | C2972: 20 | D2972: =LOOKUP(C2972,RamoAtividade!A:A,RamoAtividade!B:B) -> OUTROS SEGMENTOS | E2972: 0 | F2972: =LOOKUP(E2972,Finalidades!A:A,Finalidades!B:B) -> #N/A | G2972: N | H2972: N | I2972: N | J2972: N
A2973: 26785 | B2973: JOSE SANTOS BARCELOS | C2973: 12 | D2973: =LOOKUP(C2973,RamoAtividade!A:A,RamoAtividade!B:B) -> MODA FESTA | E2973: 0 | F2973: =LOOKUP(E2973,Finalidades!A:A,Finalidades!B:B) -> #N/A | G2973: N | H2973: N | I2973: N | J2973: N
A2974: 26788 | B2974: NADIR PETARIM - CONF | C2974: 12 | D2974: =LOOKUP(C2974,RamoAtividade!A:A,RamoAtividade!B:B) -> MODA FESTA | E2974: 0 | F2974: =LOOKUP(E2974,Finalidades!A:A,Finalidades!B:B) -> #N/A | G2974: N | H2974: N | I2974: N | J2974: N
A2975: 26789 | B2975: ELMINA VIEIRA DE GOUVEIA FER DOS SANTOS ME | C2975: 12 | D2975: =LOOKUP(C2975,RamoAtividade!A:A,RamoAtividade!B:B) -> MODA FESTA | E2975: 0 | F2975: =LOOKUP(E2975,Finalidades!A:A,Finalidades!B:B) -> #N/A | G2975: N | H2975: N | I2975: N | J2975: N
A2976: 26794 | B2976: ARTESAO DA MODA LTDA | C2976: 12 | D2976: =LOOKUP(C2976,RamoAtividade!A:A,RamoAtividade!B:B) -> MODA FESTA | E2976: 0 | F2976: =LOOKUP(E2976,Finalidades!A:A,Finalidades!B:B) -> #N/A | G2976: N | H2976: N | I2976: N | J2976: N
A2977: 26796 | B2977: J A DOS SANTOS NETO CONF | C2977: 0 | D2977: =LOOKUP(C2977,RamoAtividade!A:A,RamoAtividade!B:B) -> #N/A | E2977: 0 | F2977: =LOOKUP(E2977,Finalidades!A:A,Finalidades!B:B) -> #N/A
A2978: 26797 | B2978: VIA DO TERNO CONF LTDA ME | C2978: 0 | D2978: =LOOKUP(C2978,RamoAtividade!A:A,RamoAtividade!B:B) -> #N/A | E2978: 0 | F2978: =LOOKUP(E2978,Finalidades!A:A,Finalidades!B:B) -> #N/A
A2979: 26798 | B2979: FLORENCA TEC LTDA ME | C2979: 3 | D2979: =LOOKUP(C2979,RamoAtividade!A:A,RamoAtividade!B:B) -> CAMA, MESA,BANHO E ENXOVAL | E2979: 0 | F2979: =LOOKUP(E2979,Finalidades!A:A,Finalidades!B:B) -> #N/A | G2979: N | H2979: N | I2979: N | J2979: N
A2980: 26799 | B2980: M F CONF TEXTIL LTDA ME | C2980: 12 | D2980: =LOOKUP(C2980,RamoAtividade!A:A,RamoAtividade!B:B) -> MODA FESTA | E2980: 0 | F2980: =LOOKUP(E2980,Finalidades!A:A,Finalidades!B:B) -> #N/A | G2980: N | H2980: N | I2980: N | J2980: N
...

Sheet Finalidades
A1: Cod | B1: Descricao
A2: 1 | B2: Envio para Deposito
A3: 2 | B3: Consumo Proprio
A4: 3 | B4: Envio para Industrializa‡Æo
A5: 4 | B5: Revenda de Mercadoria

Sheet RamoAtividade
A1: Cod | B1: Descricao
A2: 1 | B2: ALFAIATARIA
A3: 2 | B3: AVIAMENTO E ARMARINHO
A4: 3 | B4: CAMA, MESA,BANHO E ENXOVAL
A5: 4 | B5: CAMISARIA
A6: 5 | B6: COM ATACADISTA DE TECIDOS
A7: 6 | B7: COM VAREJISTA DE TECIDOS
A8: 7 | B8: DECORA€ÇO, FESTAS E EVENTOS
A9: 8 | B9: FACCIONISTA
A10: 9 | B10: FEIRANTE
A11: 10 | B11: LINGERIE
A12: 11 | B12: MODA FEMININA ADULTO
A13: 12 | B13: MODA FESTA
... A21: 20 | B21: OUTROS SEGMENTOS
